thousandeyes_sdk/tags/__init__.py
thousandeyes_sdk/tags/py.typed
thousandeyes_sdk/tags/api/__init__.py
thousandeyes_sdk/tags/api/tag_assignment_api.py
thousandeyes_sdk/tags/api/tags_api.py
thousandeyes_sdk/tags/models/__init__.py
thousandeyes_sdk/tags/models/access_type.py
thousandeyes_sdk/tags/models/api_error.py
thousandeyes_sdk/tags/models/assignment.py
thousandeyes_sdk/tags/models/assignment_type.py
thousandeyes_sdk/tags/models/bulk_tag_assignment.py
thousandeyes_sdk/tags/models/bulk_tag_assignments.py
thousandeyes_sdk/tags/models/bulk_tag_response.py
thousandeyes_sdk/tags/models/error.py
thousandeyes_sdk/tags/models/expand_tags_options.py
thousandeyes_sdk/tags/models/link.py
thousandeyes_sdk/tags/models/object_type.py
thousandeyes_sdk/tags/models/self_links.py
thousandeyes_sdk/tags/models/tag.py
thousandeyes_sdk/tags/models/tag_assignment.py
thousandeyes_sdk/tags/models/tag_bulk_create_error.py
thousandeyes_sdk/tags/models/tag_info.py
thousandeyes_sdk/tags/models/tags.py
thousandeyes_sdk/tags/models/type.py
thousandeyes_sdk/tags/models/unauthorized_error.py
thousandeyes_sdk/tags/models/validation_error.py
thousandeyes_sdk/tags/models/validation_error_item.py
thousandeyes_sdk_tags-2.23.0.dist-info/licenses/LICENSE
thousandeyes_sdk_tags-2.23.0.dist-info/licenses/NOTICE
thousandeyes_sdk_tags-2.23.0.dist-info/METADATA
thousandeyes_sdk_tags-2.23.0.dist-info/WHEEL
thousandeyes_sdk_tags-2.23.0.dist-info/top_level.txt
thousandeyes_sdk_tags-2.23.0.dist-info/RECORD
