Metadata-Version: 2.4
Name: thousandeyes-sdk-tags
Version: 2.23.0
Summary: ThousandEyes SDK Tags API
Author-email: ThousandEyes API Team <api-team@thousandeyes.com>
License:                                  Apache License
Requires-Python: >=3.8
License-File: LICENSE
License-File: NOTICE
Requires-Dist: urllib3>=2.0.0
Requires-Dist: python-dateutil>=2.8.2
Requires-Dist: pydantic>=2.1.0
Requires-Dist: typing-extensions>=4.7.1
Requires-Dist: thousandeyes-sdk-core
Provides-Extra: test
Requires-Dist: pytest~=7.1.3; extra == "test"
Requires-Dist: pytest-cov>=2.8.1; extra == "test"
Requires-Dist: pytest-randomly>=3.12.0; extra == "test"
Requires-Dist: mypy>=1.4.1; extra == "test"
Requires-Dist: types-python-dateutil>=2.8.19; extra == "test"
Provides-Extra: dev
Requires-Dist: flake8>=4.0.0; extra == "dev"
Requires-Dist: mypy>=1.4.1; extra == "dev"
Requires-Dist: types-python-dateutil>=2.8.19; extra == "dev"
Dynamic: license-file
